README.rst
setup.py
dirty_loader/__init__.py
dirty_loader/factories.py
dirty_loader.egg-info/PKG-INFO
dirty_loader.egg-info/SOURCES.txt
dirty_loader.egg-info/dependency_links.txt
dirty_loader.egg-info/top_level.txt
dirty_loader.egg-info/zip-safe