Metadata-Version: 1.1
Name: dirty-loader
Version: 0.2.2
Summary: Dirty loader for python 3
Home-page: https://github.com/alfred82santa/dirty-loader
Author: alfred82santa
Author-email: alfred82santa@gmail.com
License: LGPLv2.1
Platform: UNKNOWN
Classifier: Intended Audience :: Developers
Classifier: Programming Language :: Python
Classifier: Programming Language :: Python :: 3.3
Classifier: Programming Language :: Python :: 3.4
Classifier: Programming Language :: Python :: 3.5
